pyafs/__init__.py
pyafs/afs.py
pyafs/core/__init__.py
pyafs/core/afs_filtering.py
pyafs/core/afs_final_blaze.py
pyafs/core/alpha_shape.py
pyafs/core/interpolate.py
pyafs/core/mark_outlier.py
pyafs/core/primitive_blaze.py
pyafs/core/scale.py
pyafs/core/smooth.py
pyafs/graphics/__init__.py
pyafs/graphics/alpha_shape.py
pyafs/graphics/filtering.py
pyafs/graphics/mark_outlier.py
pyafs/graphics/norm_blaze.py
pyafs/graphics/spec.py
pyafs/graphics/utils.py
pyafs_astro-0.2.0.dist-info/LICENSE
pyafs_astro-0.2.0.dist-info/METADATA
pyafs_astro-0.2.0.dist-info/WHEEL
pyafs_astro-0.2.0.dist-info/RECORD
