Metadata-Version: 2.1
Name: pyafs-astro
Version: 0.2.0
Summary: A Python implementation of Alpha-shape Fitting to Spectrum (AFS) algorithm
Home-page: https://github.com/fengshun124/pyAFS
License: GPL-3.0-or-later
Author: Yifan Wang
Author-email: fengshun124@outlook.com
Requires-Python: >=3.10
Classifier: License :: OSI Approved :: GNU General Public License v3 or later (GPLv3+)
Classifier: Programming Language :: Python :: 3
Classifier: Programming Language :: Python :: 3.10
Classifier: Programming Language :: Python :: 3.11
Classifier: Programming Language :: Python :: 3.12
Classifier: Programming Language :: Python :: 3.13
Requires-Dist: alphashape
Requires-Dist: loess
Requires-Dist: matplotlib
Requires-Dist: numpy
Requires-Dist: pandas
Requires-Dist: scipy
Requires-Dist: shapely
Project-URL: Repository, https://github.com/fengshun124/pyAFS
